{
  "environment_id": "wooded_path_and_hall",
  "display_name": "wooded_path_and_hall",
  "environment_type": "unknown",
  "status": "canonical",
  "entity_kind": "environment",
  "first_seen_chapter": "CH007",
  "last_seen_chapter": "CH007",
  "chapter_mentions": [
    "CH007"
  ],
  "visual_summary": "The environment is currently defined by its canonical ID, with specific visual details pending further extraction.",
  "layout_notes": "Unknown.",
  "lighting": "Unknown.",
  "mood": "Unknown.",
  "recurring_elements": [
    "None identified"
  ],
  "constraints": [
    "Visual identity must align with the name \"wooded_path_and_hall\" as per canonical ID."
  ],
  "unresolved_ambiguities": [
    "Specific visual characteristics of the wooded path and hall are not yet described in the provided evidence."
  ],
  "evidence_refs": [
    {
      "source": "registry_chapter_specific",
      "chapter_id": null,
      "source_path": "projects/alice_in_wonderland/02_story_analysis/environment_breakdowns/chapters/CH007/wooded_path_and_hall.md"
    }
  ],
  "evidence_summary": [
    "Environment currently kept under extracted canonical id."
  ],
  "metadata": {
    "artifact_id": "ENV_wooded_path_and_hall",
    "artifact_type": "environment_bible",
    "status": "generated",
    "source_fingerprint": "8d4d57d8bb98443ea04ddded6d9876327ccd0b20",
    "created_at_utc": "2026-04-28T00:26:51.584323+00:00",
    "updated_at_utc": "2026-04-28T00:26:51.584323+00:00",
    "upstream_dependencies": [
      {
        "dependency_type": "environment_registry_entry",
        "dependency_id": "wooded_path_and_hall",
        "version": "8d4d57d8bb98443ea04ddded6d9876327ccd0b20"
      }
    ],
    "locked_fields": {},
    "manual_overrides": {},
    "revision_history": [
      {
        "timestamp_utc": "2026-04-28T00:26:58.995232+00:00",
        "action": "synthesized",
        "source_fingerprint": "8d4d57d8bb98443ea04ddded6d9876327ccd0b20"
      }
    ]
  }
}
