[
  {
    "dialogue_id": "CH007_DLG060",
    "chapter_id": "CH007",
    "paragraph_index": 43,
    "quote_index": 1,
    "source_ref": "CH007:p043:q01",
    "source_path": "projects/alice_in_wonderland/01_source/chapters/CH007_chapter_vii.md",
    "dialogue_text": "Perhaps not,",
    "source_excerpt": "\"Perhaps not,\" Alice cautiously replied: \"but I know I have to beat time when I learn music.\"",
    "speaker": {
      "speaker_label": "Alice cautiously",
      "canonical_id": "alice",
      "display_name": "alice",
      "status": "canonical",
      "entity_kind": "individual",
      "confidence": 0.74,
      "resolution_method": "attribution_name",
      "notes": "Matched speaker phrase 'Alice cautiously' to 'alice'."
    },
    "scene_id": "CH007_SC003",
    "shot_id": "SH004",
    "clip_id": "CL004",
    "scene_binding_confidence": 0.55,
    "shot_binding_confidence": 0.45,
    "binding_method": "shot_sequence",
    "review_notes": []
  }
]
