{
  "environment_id": "wizard_camp_area",
  "display_name": "wizard_camp_area",
  "environment_type": "Secondary setting; transition space between the grand throne room and the outside world.",
  "status": "canonical",
  "entity_kind": "environment",
  "first_seen_chapter": "CH016",
  "last_seen_chapter": "CH016",
  "chapter_mentions": [
    "CH016"
  ],
  "visual_summary": "No specific visual details are provided in the current evidence. The area functions primarily as a transitional zone connecting the interior grand throne room to the exterior world.",
  "layout_notes": "Serves as a spatial bridge between the grand throne room and the outside world.",
  "lighting": "Unknown",
  "mood": "Unknown",
  "recurring_elements": [
    "None identified"
  ],
  "constraints": [
    "Must function as a transition space between the throne room and the exterior."
  ],
  "unresolved_ambiguities": [
    "Specific visual characteristics of the camp area are currently undocumented.",
    "The exact physical nature of the \"camp\" (e.g., temporary structures, terrain) is unknown."
  ],
  "evidence_refs": [
    {
      "source": "registry_chapter_specific",
      "chapter_id": null,
      "source_path": "projects/wizard_of_oz/02_story_analysis/environment_breakdowns/chapters/CH016/wizard_camp_area.md"
    },
    {
      "source": "environment_breakdown_markdown",
      "chapter_id": "CH016",
      "source_path": "projects/wizard_of_oz/02_story_analysis/environment_breakdowns/chapters/CH016/wizard_camp_area.md"
    },
    {
      "source": "book_index",
      "chapter_id": "CH010",
      "source_path": null
    },
    {
      "source": "book_index",
      "chapter_id": "CH018",
      "source_path": null
    },
    {
      "source": "book_index",
      "chapter_id": "CH019",
      "source_path": null
    }
  ],
  "evidence_summary": [
    "Environment currently kept under extracted canonical id.",
    "Role: Secondary setting; transition space between the grand throne room and the outside world.",
    "[CH010] Chapter X (book index hit)",
    "[CH018] Chapter XVIII (book index hit)",
    "[CH019] Chapter XIX (book index hit)"
  ],
  "metadata": {
    "artifact_id": "ENV_wizard_camp_area",
    "artifact_type": "environment_bible",
    "status": "generated",
    "source_fingerprint": "0ce96166714fdc91406ddf6c72ec74a837c62555",
    "created_at_utc": "2026-04-27T07:54:31.530251+00:00",
    "updated_at_utc": "2026-04-27T07:54:31.530251+00:00",
    "upstream_dependencies": [
      {
        "dependency_type": "environment_registry_entry",
        "dependency_id": "wizard_camp_area",
        "version": "0ce96166714fdc91406ddf6c72ec74a837c62555"
      }
    ],
    "locked_fields": {},
    "manual_overrides": {},
    "revision_history": [
      {
        "timestamp_utc": "2026-04-27T07:54:42.451133+00:00",
        "action": "synthesized",
        "source_fingerprint": "0ce96166714fdc91406ddf6c72ec74a837c62555"
      }
    ]
  }
}
