{
  "character_id": "toto",
  "display_name": "toto",
  "entity_kind": "individual",
  "primary_type": "animal",
  "morphology": "quadruped",
  "scale": "unknown",
  "sentience": "animal",
  "renderability": "renderable",
  "confidence": 1.0,
  "direct_evidence": [
    "animal",
    "animal",
    "animal",
    "animal",
    "animal",
    "animal",
    "animal",
    "animal",
    "animal",
    "animal",
    "animal",
    "animal",
    "animal",
    "animal",
    "animal",
    "animal",
    "animal",
    "animal",
    "animal"
  ],
  "direct_evidence_records": [
    {
      "type_hint": "animal",
      "morphology_hint": "quadruped",
      "scale_hint": "small",
      "renderability_hint": "renderable",
      "confidence": 1.0,
      "direct_identity_evidence": "Named as Dorothy's dog.",
      "direct_visual_evidence": "Small, energetic, black.",
      "costume_or_covering_evidence": "Black fur.",
      "movement_evidence": "Energetic; nearly falls through a trap door; rescued by Dorothy.",
      "source_path": "C:\\FilmCreator\\projects\\wizard_of_oz\\02_story_analysis\\character_breakdowns\\chapters\\CH001\\toto.md",
      "source_refs": [
        "Chapter 1\nNone\ntoto\ntrue\nNo\nNone"
      ]
    },
    {
      "type_hint": "animal",
      "morphology_hint": "quadruped",
      "scale_hint": "tiny",
      "renderability_hint": "renderable",
      "confidence": 1.0,
      "direct_identity_evidence": "Toto is explicitly named as Dorothy's small dog.",
      "direct_visual_evidence": "Small dog.",
      "costume_or_covering_evidence": "",
      "movement_evidence": "",
      "source_path": "C:\\FilmCreator\\projects\\wizard_of_oz\\02_story_analysis\\character_breakdowns\\chapters\\CH002\\toto.md",
      "source_refs": [
        "Small dog\ntoto\ntrue\nNo\nNone"
      ]
    },
    {
      "type_hint": "animal",
      "morphology_hint": "quadruped",
      "scale_hint": "small",
      "renderability_hint": "renderable",
      "confidence": 0.9,
      "direct_identity_evidence": "Toto is named as Dorothy's dog.",
      "direct_visual_evidence": "Identified as a dog.",
      "costume_or_covering_evidence": "",
      "movement_evidence": "Traveling with Dorothy, acting skeptical of the Scarecrow.",
      "source_path": "C:\\FilmCreator\\projects\\wizard_of_oz\\02_story_analysis\\character_breakdowns\\chapters\\CH003\\toto.md",
      "source_refs": [
        "Dog\ntoto\ntrue\nNo\nNone"
      ]
    },
    {
      "type_hint": "animal",
      "morphology_hint": "quadruped",
      "scale_hint": "small",
      "renderability_hint": "renderable",
      "confidence": 0.9,
      "direct_identity_evidence": "true",
      "direct_visual_evidence": "false",
      "costume_or_covering_evidence": "false",
      "movement_evidence": "true",
      "source_path": "C:\\FilmCreator\\projects\\wizard_of_oz\\02_story_analysis\\character_breakdowns\\chapters\\CH004\\toto.md",
      "source_refs": [
        "[CH004]\nDog\ntoto\ntrue\nNo\nNone"
      ]
    },
    {
      "type_hint": "animal",
      "morphology_hint": "quadruped",
      "scale_hint": "small",
      "renderability_hint": "renderable",
      "confidence": 1.0,
      "direct_identity_evidence": "Named as Toto; identified as Dorothy's dog.",
      "direct_visual_evidence": "None provided in text.",
      "costume_or_covering_evidence": "None.",
      "movement_evidence": "Traveling with Dorothy.",
      "source_path": "C:\\FilmCreator\\projects\\wizard_of_oz\\02_story_analysis\\character_breakdowns\\chapters\\CH005\\toto.md",
      "source_refs": [
        "CH005\nDog\ntoto\ntrue\nYes\nBreed and physical appearance not specified."
      ]
    },
    {
      "type_hint": "animal",
      "morphology_hint": "quadruped",
      "scale_hint": "small",
      "renderability_hint": "renderable",
      "confidence": 0.9,
      "direct_identity_evidence": "true",
      "direct_visual_evidence": "false",
      "costume_or_covering_evidence": "false",
      "movement_evidence": "true",
      "source_path": "C:\\FilmCreator\\projects\\wizard_of_oz\\02_story_analysis\\character_breakdowns\\chapters\\CH006\\toto.md",
      "source_refs": [
        "Dog\ntoto\ntrue\nNo\nNone"
      ]
    },
    {
      "type_hint": "animal",
      "morphology_hint": "quadruped",
      "scale_hint": "small",
      "renderability_hint": "renderable",
      "confidence": 0.9,
      "direct_identity_evidence": "\"Dorothy (and Toto)\"",
      "direct_visual_evidence": "\"\"",
      "costume_or_covering_evidence": "\"\"",
      "movement_evidence": "\"\"",
      "source_path": "C:\\FilmCreator\\projects\\wizard_of_oz\\02_story_analysis\\character_breakdowns\\chapters\\CH007\\toto.md",
      "source_refs": [
        "None\ntoto\ntrue\nNo\nNone"
      ]
    },
    {
      "type_hint": "animal",
      "morphology_hint": "quadruped",
      "scale_hint": "small",
      "renderability_hint": "renderable",
      "confidence": 0.9,
      "direct_identity_evidence": "Yes",
      "direct_visual_evidence": "No",
      "costume_or_covering_evidence": "No",
      "movement_evidence": "Yes",
      "source_path": "C:\\FilmCreator\\projects\\wizard_of_oz\\02_story_analysis\\character_breakdowns\\chapters\\CH008\\toto.md",
      "source_refs": [
        "None\ntoto\ntrue\nNo\nNone"
      ]
    },
    {
      "type_hint": "animal",
      "morphology_hint": "quadruped",
      "scale_hint": "small",
      "renderability_hint": "renderable",
      "confidence": 0.9,
      "direct_identity_evidence": "Toto is named as attempting to chase the mice.",
      "direct_visual_evidence": "",
      "costume_or_covering_evidence": "",
      "movement_evidence": "Attempts to chase field mice.",
      "source_path": "C:\\FilmCreator\\projects\\wizard_of_oz\\02_story_analysis\\character_breakdowns\\chapters\\CH009\\toto.md",
      "source_refs": [
        "None\ntoto\ntrue\nNo\nNone"
      ]
    },
    {
      "type_hint": "animal",
      "morphology_hint": "quadruped",
      "scale_hint": "small",
      "renderability_hint": "renderable",
      "confidence": 0.9,
      "direct_identity_evidence": "Toto is Dorothy's dog.",
      "direct_visual_evidence": "",
      "costume_or_covering_evidence": "Wears green-lensed spectacles (locked on).",
      "movement_evidence": "",
      "source_path": "C:\\FilmCreator\\projects\\wizard_of_oz\\02_story_analysis\\character_breakdowns\\chapters\\CH010\\toto.md",
      "source_refs": [
        "None\ntoto\ntrue\nNo\nNone"
      ]
    },
    {
      "type_hint": "animal",
      "morphology_hint": "quadruped",
      "scale_hint": "small",
      "renderability_hint": "renderable",
      "confidence": 1.0,
      "direct_identity_evidence": "Traveling with Dorothy.",
      "direct_visual_evidence": "",
      "costume_or_covering_evidence": "",
      "movement_evidence": "",
      "source_path": "C:\\FilmCreator\\projects\\wizard_of_oz\\02_story_analysis\\character_breakdowns\\chapters\\CH011\\toto.md",
      "source_refs": [
        "None\ntoto\ntrue\nNo\nNone"
      ]
    },
    {
      "type_hint": "animal",
      "morphology_hint": "quadruped",
      "scale_hint": "small",
      "renderability_hint": "renderable",
      "confidence": 1.0,
      "direct_identity_evidence": "Named as Toto; traveling with Dorothy.",
      "direct_visual_evidence": "",
      "costume_or_covering_evidence": "",
      "movement_evidence": "Traveling with the group.",
      "source_path": "C:\\FilmCreator\\projects\\wizard_of_oz\\02_story_analysis\\character_breakdowns\\chapters\\CH012\\toto.md",
      "source_refs": [
        "None\ntoto\ntrue\nNo\nNone"
      ]
    },
    {
      "type_hint": "animal",
      "morphology_hint": "quadruped",
      "scale_hint": "small",
      "renderability_hint": "renderable",
      "confidence": 1.0,
      "direct_identity_evidence": "Named as Toto.",
      "direct_visual_evidence": "Present in chapter.",
      "costume_or_covering_evidence": "",
      "movement_evidence": "Traveling with the group.",
      "source_path": "C:\\FilmCreator\\projects\\wizard_of_oz\\02_story_analysis\\character_breakdowns\\chapters\\CH014\\toto.md",
      "source_refs": [
        "None\ntoto\ntrue\nNo\nNone"
      ]
    },
    {
      "type_hint": "animal",
      "morphology_hint": "quadruped",
      "scale_hint": "small",
      "renderability_hint": "renderable",
      "confidence": 1.0,
      "direct_identity_evidence": "Yes",
      "direct_visual_evidence": "Yes",
      "costume_or_covering_evidence": "No",
      "movement_evidence": "Yes",
      "source_path": "C:\\FilmCreator\\projects\\wizard_of_oz\\02_story_analysis\\character_breakdowns\\chapters\\CH019\\toto.md",
      "source_refs": [
        "None\ntoto\ntrue\nNo\nNone"
      ]
    },
    {
      "type_hint": "animal",
      "morphology_hint": "quadruped",
      "scale_hint": "small",
      "renderability_hint": "renderable",
      "confidence": 1.0,
      "direct_identity_evidence": "Toto is explicitly named as part of the traveling group.",
      "direct_visual_evidence": "Present in the scene.",
      "costume_or_covering_evidence": "",
      "movement_evidence": "Traveling with the group.",
      "source_path": "C:\\FilmCreator\\projects\\wizard_of_oz\\02_story_analysis\\character_breakdowns\\chapters\\CH020\\toto.md",
      "source_refs": [
        "None\ntoto\ntrue\nNo\nNone"
      ]
    },
    {
      "type_hint": "animal",
      "morphology_hint": "quadruped",
      "scale_hint": "small",
      "renderability_hint": "renderable",
      "confidence": 0.9,
      "direct_identity_evidence": "Traveling with Dorothy.",
      "direct_visual_evidence": "",
      "costume_or_covering_evidence": "",
      "movement_evidence": "Navigating through difficult marshlands.",
      "source_path": "C:\\FilmCreator\\projects\\wizard_of_oz\\02_story_analysis\\character_breakdowns\\chapters\\CH021\\toto.md",
      "source_refs": [
        "None\ntoto\ntrue\nNo\nNone"
      ]
    },
    {
      "type_hint": "animal",
      "morphology_hint": "quadruped",
      "scale_hint": "tiny",
      "renderability_hint": "renderable",
      "confidence": 1.0,
      "direct_identity_evidence": "true",
      "direct_visual_evidence": "false",
      "costume_or_covering_evidence": "false",
      "movement_evidence": "true",
      "source_path": "C:\\FilmCreator\\projects\\wizard_of_oz\\02_story_analysis\\character_breakdowns\\chapters\\CH022\\toto.md",
      "source_refs": [
        "None\ntoto\ntrue\nNo\nNone"
      ]
    },
    {
      "type_hint": "animal",
      "morphology_hint": "quadruped",
      "scale_hint": "tiny",
      "renderability_hint": "renderable",
      "confidence": 0.5,
      "direct_identity_evidence": "Explicitly named as Toto.",
      "direct_visual_evidence": "None.",
      "costume_or_covering_evidence": "None.",
      "movement_evidence": "Appears in the final scene on the Kansas prairie.",
      "source_path": "C:\\FilmCreator\\projects\\wizard_of_oz\\02_story_analysis\\character_breakdowns\\chapters\\CH023\\toto.md",
      "source_refs": [
        "None\ntoto\ntrue\nYes\nNo physical description provided in the text."
      ]
    },
    {
      "type_hint": "animal",
      "morphology_hint": "quadruped",
      "scale_hint": "small",
      "renderability_hint": "renderable",
      "confidence": 1.0,
      "direct_identity_evidence": "\"accompanied by Toto\"",
      "direct_visual_evidence": "",
      "costume_or_covering_evidence": "",
      "movement_evidence": "",
      "source_path": "C:\\FilmCreator\\projects\\wizard_of_oz\\02_story_analysis\\character_breakdowns\\chapters\\CH024\\toto.md",
      "source_refs": [
        "[]\n[]\ntoto\ntrue\nNo\nNone"
      ]
    }
  ],
  "associated_evidence": [
    "Dorothy",
    "Dorothy",
    "Dorothy",
    "[dorothy]",
    "Dorothy",
    "Dorothy",
    "Dorothy",
    "Dorothy",
    "Dorothy",
    "Dorothy",
    "Dorothy",
    "Dorothy",
    "Dorothy",
    "Scarecrow",
    "Tin Woodman",
    "Cowardly Lion",
    "Dorothy",
    "Scarecrow",
    "Tin Woodman",
    "Cowardly Lion",
    "Dorothy",
    "Scarecrow",
    "Tin Woodman",
    "Cowardly Lion",
    "Dorothy",
    "Dorothy",
    "Dorothy",
    "Uncle Henry",
    "[\"Dorothy\"]"
  ],
  "associated_evidence_records": [
    {
      "associated_entities": [
        "Dorothy"
      ],
      "source_path": "C:\\FilmCreator\\projects\\wizard_of_oz\\02_story_analysis\\character_breakdowns\\chapters\\CH001\\toto.md",
      "source_refs": [
        "Chapter 1\nNone\ntoto\ntrue\nNo\nNone"
      ]
    },
    {
      "associated_entities": [
        "Dorothy"
      ],
      "source_path": "C:\\FilmCreator\\projects\\wizard_of_oz\\02_story_analysis\\character_breakdowns\\chapters\\CH002\\toto.md",
      "source_refs": [
        "Small dog\ntoto\ntrue\nNo\nNone"
      ]
    },
    {
      "associated_entities": [
        "Dorothy"
      ],
      "source_path": "C:\\FilmCreator\\projects\\wizard_of_oz\\02_story_analysis\\character_breakdowns\\chapters\\CH003\\toto.md",
      "source_refs": [
        "Dog\ntoto\ntrue\nNo\nNone"
      ]
    },
    {
      "associated_entities": [
        "[dorothy]"
      ],
      "source_path": "C:\\FilmCreator\\projects\\wizard_of_oz\\02_story_analysis\\character_breakdowns\\chapters\\CH004\\toto.md",
      "source_refs": [
        "[CH004]\nDog\ntoto\ntrue\nNo\nNone"
      ]
    },
    {
      "associated_entities": [
        "Dorothy"
      ],
      "source_path": "C:\\FilmCreator\\projects\\wizard_of_oz\\02_story_analysis\\character_breakdowns\\chapters\\CH005\\toto.md",
      "source_refs": [
        "CH005\nDog\ntoto\ntrue\nYes\nBreed and physical appearance not specified."
      ]
    },
    {
      "associated_entities": [
        "Dorothy"
      ],
      "source_path": "C:\\FilmCreator\\projects\\wizard_of_oz\\02_story_analysis\\character_breakdowns\\chapters\\CH006\\toto.md",
      "source_refs": [
        "Dog\ntoto\ntrue\nNo\nNone"
      ]
    },
    {
      "associated_entities": [
        "Dorothy"
      ],
      "source_path": "C:\\FilmCreator\\projects\\wizard_of_oz\\02_story_analysis\\character_breakdowns\\chapters\\CH007\\toto.md",
      "source_refs": [
        "None\ntoto\ntrue\nNo\nNone"
      ]
    },
    {
      "associated_entities": [
        "Dorothy"
      ],
      "source_path": "C:\\FilmCreator\\projects\\wizard_of_oz\\02_story_analysis\\character_breakdowns\\chapters\\CH008\\toto.md",
      "source_refs": [
        "None\ntoto\ntrue\nNo\nNone"
      ]
    },
    {
      "associated_entities": [
        "Dorothy"
      ],
      "source_path": "C:\\FilmCreator\\projects\\wizard_of_oz\\02_story_analysis\\character_breakdowns\\chapters\\CH009\\toto.md",
      "source_refs": [
        "None\ntoto\ntrue\nNo\nNone"
      ]
    },
    {
      "associated_entities": [
        "Dorothy"
      ],
      "source_path": "C:\\FilmCreator\\projects\\wizard_of_oz\\02_story_analysis\\character_breakdowns\\chapters\\CH010\\toto.md",
      "source_refs": [
        "None\ntoto\ntrue\nNo\nNone"
      ]
    },
    {
      "associated_entities": [
        "Dorothy"
      ],
      "source_path": "C:\\FilmCreator\\projects\\wizard_of_oz\\02_story_analysis\\character_breakdowns\\chapters\\CH011\\toto.md",
      "source_refs": [
        "None\ntoto\ntrue\nNo\nNone"
      ]
    },
    {
      "associated_entities": [
        "Dorothy"
      ],
      "source_path": "C:\\FilmCreator\\projects\\wizard_of_oz\\02_story_analysis\\character_breakdowns\\chapters\\CH012\\toto.md",
      "source_refs": [
        "None\ntoto\ntrue\nNo\nNone"
      ]
    },
    {
      "associated_entities": [
        "Dorothy",
        "Scarecrow",
        "Tin Woodman",
        "Cowardly Lion"
      ],
      "source_path": "C:\\FilmCreator\\projects\\wizard_of_oz\\02_story_analysis\\character_breakdowns\\chapters\\CH014\\toto.md",
      "source_refs": [
        "None\ntoto\ntrue\nNo\nNone"
      ]
    },
    {
      "associated_entities": [
        "Dorothy",
        "Scarecrow",
        "Tin Woodman",
        "Cowardly Lion"
      ],
      "source_path": "C:\\FilmCreator\\projects\\wizard_of_oz\\02_story_analysis\\character_breakdowns\\chapters\\CH019\\toto.md",
      "source_refs": [
        "None\ntoto\ntrue\nNo\nNone"
      ]
    },
    {
      "associated_entities": [
        "Dorothy",
        "Scarecrow",
        "Tin Woodman",
        "Cowardly Lion"
      ],
      "source_path": "C:\\FilmCreator\\projects\\wizard_of_oz\\02_story_analysis\\character_breakdowns\\chapters\\CH020\\toto.md",
      "source_refs": [
        "None\ntoto\ntrue\nNo\nNone"
      ]
    },
    {
      "associated_entities": [
        "Dorothy"
      ],
      "source_path": "C:\\FilmCreator\\projects\\wizard_of_oz\\02_story_analysis\\character_breakdowns\\chapters\\CH021\\toto.md",
      "source_refs": [
        "None\ntoto\ntrue\nNo\nNone"
      ]
    },
    {
      "associated_entities": [
        "Dorothy"
      ],
      "source_path": "C:\\FilmCreator\\projects\\wizard_of_oz\\02_story_analysis\\character_breakdowns\\chapters\\CH022\\toto.md",
      "source_refs": [
        "None\ntoto\ntrue\nNo\nNone"
      ]
    },
    {
      "associated_entities": [
        "Dorothy",
        "Uncle Henry"
      ],
      "source_path": "C:\\FilmCreator\\projects\\wizard_of_oz\\02_story_analysis\\character_breakdowns\\chapters\\CH023\\toto.md",
      "source_refs": [
        "None\ntoto\ntrue\nYes\nNo physical description provided in the text."
      ]
    },
    {
      "associated_entities": [
        "[\"Dorothy\"]"
      ],
      "source_path": "C:\\FilmCreator\\projects\\wizard_of_oz\\02_story_analysis\\character_breakdowns\\chapters\\CH024\\toto.md",
      "source_refs": [
        "[]\n[]\ntoto\ntrue\nNo\nNone"
      ]
    }
  ],
  "conflicts": [
    "Conflicting scale hints: ['small', 'tiny', 'small', 'small', 'small', 'small', 'small', 'small', 'small', 'small', 'small', 'small', 'small', 'small', 'small', 'small', 'tiny', 'tiny', 'small']"
  ],
  "unknowns": [
    "scale"
  ],
  "needs_review": true,
  "review_reasons": [
    "Conflicting taxonomy hints detected"
  ],
  "alias_resolution": {
    "status": "canonical",
    "canonical_target_id": null,
    "confidence": 1.0,
    "evidence": [
      "Registry status is canonical"
    ],
    "requires_human_review": false
  },
  "source_files": [
    "projects/wizard_of_oz/02_story_analysis/character_breakdowns/chapters/CH001/toto.md",
    "projects/wizard_of_oz/02_story_analysis/character_breakdowns/chapters/CH002/toto.md",
    "projects/wizard_of_oz/02_story_analysis/character_breakdowns/chapters/CH003/toto.md",
    "projects/wizard_of_oz/02_story_analysis/character_breakdowns/chapters/CH004/toto.md",
    "projects/wizard_of_oz/02_story_analysis/character_breakdowns/chapters/CH005/toto.md",
    "projects/wizard_of_oz/02_story_analysis/character_breakdowns/chapters/CH006/toto.md",
    "projects/wizard_of_oz/02_story_analysis/character_breakdowns/chapters/CH007/toto.md",
    "projects/wizard_of_oz/02_story_analysis/character_breakdowns/chapters/CH008/toto.md",
    "projects/wizard_of_oz/02_story_analysis/character_breakdowns/chapters/CH009/toto.md",
    "projects/wizard_of_oz/02_story_analysis/character_breakdowns/chapters/CH010/toto.md",
    "projects/wizard_of_oz/02_story_analysis/character_breakdowns/chapters/CH011/toto.md",
    "projects/wizard_of_oz/02_story_analysis/character_breakdowns/chapters/CH012/toto.md",
    "projects/wizard_of_oz/02_story_analysis/character_breakdowns/chapters/CH014/toto.md",
    "projects/wizard_of_oz/02_story_analysis/character_breakdowns/chapters/CH019/toto.md",
    "projects/wizard_of_oz/02_story_analysis/character_breakdowns/chapters/CH020/toto.md",
    "projects/wizard_of_oz/02_story_analysis/character_breakdowns/chapters/CH021/toto.md",
    "projects/wizard_of_oz/02_story_analysis/character_breakdowns/chapters/CH022/toto.md",
    "projects/wizard_of_oz/02_story_analysis/character_breakdowns/chapters/CH023/toto.md",
    "projects/wizard_of_oz/02_story_analysis/character_breakdowns/chapters/CH024/toto.md"
  ],
  "generated_at_utc": "2026-04-27T12:50:35.795140+00:00"
}
