{
  "chapter_id": "CH006",
  "scene_order": [
    "CH006_SC001",
    "CH006_SC002",
    "CH006_SC003",
    "CH006_SC004"
  ],
  "known_characters": [
    "alice",
    "alice_s_sister",
    "baby_pig",
    "blue_caterpillar",
    "canary",
    "cheshire_cat",
    "cook",
    "dinah",
    "dodo",
    "duck",
    "eaglet",
    "enormous_puppy",
    "fish_footman",
    "frog_footman",
    "lory",
    "mad_hatter",
    "magpie",
    "march_hare",
    "old_crab",
    "pat_laborer",
    "queen_of_hearts",
    "the_duchess",
    "white_rabbit",
    "young_crab"
  ],
  "known_environments": [
    "caucus_race_course",
    "duchess_kitchen_interior",
    "field_and_hedge_setting",
    "hallway_of_doors",
    "march_hare_house_exterior",
    "miniature_garden_view",
    "rabbit_hole_descent",
    "riverbank_assembly",
    "riverbank_setting",
    "the_hall",
    "the_pool_of_tears",
    "the_wood",
    "white_rabbits_house",
    "woods_and_house_exterior"
  ],
  "unresolved_character_ids": [],
  "world_registry_paths": [
    "projects/alice_in_wonderland/02_story_analysis/world/CHARACTER_REGISTRY.json",
    "projects/alice_in_wonderland/02_story_analysis/world/ENVIRONMENT_REGISTRY.json"
  ],
  "snapshot_path": "projects/alice_in_wonderland/02_story_analysis/world/snapshots/CH006_WORLD_SNAPSHOT.json",
  "generated_at_utc": "2026-04-28T03:38:20.916537+00:00"
}
