{
  "scene_id": "CH017_SC004",
  "chapter_id": "CH017",
  "scene_title": "SC004",
  "purpose": "The climax of the chapter and the tragic reversal of fortune.",
  "summary": "As the balloon begins to lift, Dorothy realizes Toto is missing and rushes to find him. Just as she reaches the basket, the ropes snap prematurely. The balloon ascends rapidly into the sky with only Oz inside, leaving Dorothy and her friends stranded on the ground.",
  "emotional_arc": "From frantic hope to sudden shock and abandonment.",
  "production_intent": "Execute the tragic separation of Dorothy and Oz via a mechanical failure of the balloon tethering system. The sequence must transition from high-energy movement to static despair, emphasizing the vertical distance growing between the characters on the ground and the ascending vessel.",
  "scene_short_description": "A character rushes toward a lifting vessel just as the tethers fail, causing an immediate vertical separation.",
  "scene_primary_scale_story_point": "The growing vertical gap between the ground-bound group and the ascending balloon.",
  "scene_required_anchor_catalog": [
    "balloon_basket",
    "tether_ropes"
  ],
  "scene_start_state": "Dorothy realizes Toto is missing while the balloon begins its initial lift.",
  "scene_end_state": "The balloon is a small object in the sky; Dorothy and friends are stationary on the ground.",
  "dominant_action_line": "Dorothy runs for the basket, the ropes snap, and the balloon ascends rapidly with Oz inside.",
  "scene_spatial_layout": [
    "Vertical axis priority (ground to sky)",
    "Open launch area near palace exterior"
  ],
  "character_spatial_map": [
    "dorothy: moving from mid-ground toward balloon_basket",
    "oz: contained within balloon_basket",
    "the_scarecrow, tin_woodman, Lion: clustered on ground near launch site"
  ],
  "environment_subzones": [
    "balloon_launch_platform",
    "emerald_city_palace_exterior"
  ],
  "entry_vectors": [
    "dorothy running from off-screen toward basket"
  ],
  "exit_vectors": [
    "oz ascending vertically out of frame"
  ],
  "beat_transition_map": [
    "BT001 -> BT002: sudden mechanical failure",
    "BT002 -> BT003: rapid vertical ascent"
  ],
  "characters_required": [
    {
      "label": "Dorothy",
      "canonical_id": "dorothy",
      "display_name": "dorothy",
      "status": "canonical",
      "entity_kind": "individual",
      "resolution_score": 138,
      "source_path": "projects/wizard_of_oz/02_story_analysis/character_breakdowns/chapters/CH017/dorothy.md",
      "notes": "Direct registry match for 'dorothy'."
    },
    {
      "label": "Oz (The Wizard)",
      "canonical_id": "oz",
      "display_name": "oz",
      "status": "canonical",
      "entity_kind": "individual",
      "resolution_score": 138,
      "source_path": "projects/wizard_of_oz/02_story_analysis/character_breakdowns/chapters/CH017/oz_the_wizard.md",
      "notes": "Direct registry match for 'oz_the_wizard'."
    },
    {
      "label": "Scarecrow",
      "canonical_id": "the_scarecrow",
      "display_name": "the_scarecrow",
      "status": "canonical",
      "entity_kind": "individual",
      "resolution_score": 186,
      "source_path": "projects/wizard_of_oz/02_story_analysis/character_breakdowns/chapters/CH003/the_scarecrow.md",
      "notes": "asset id exactly matches canonical id | query matches alias 'scarecrow'"
    },
    {
      "label": "Tin Woodman",
      "canonical_id": "tin_woodman",
      "display_name": "tin_woodman",
      "status": "canonical",
      "entity_kind": "individual",
      "resolution_score": 138,
      "source_path": "projects/wizard_of_oz/02_story_analysis/character_breakdowns/chapters/CH017/tin_woodman.md",
      "notes": "Direct registry match for 'tin_woodman'."
    },
    {
      "label": "Lion",
      "canonical_id": null,
      "display_name": "Lion",
      "status": "review",
      "entity_kind": "individual",
      "resolution_score": 16,
      "source_path": "",
      "notes": "Low-confidence character match requires review."
    },
    {
      "label": "Toto (off-screen/searching)",
      "canonical_id": "toto",
      "display_name": "toto",
      "status": "canonical",
      "entity_kind": "individual",
      "resolution_score": 124,
      "source_path": "projects/wizard_of_oz/02_story_analysis/character_breakdowns/chapters/CH001/toto.md",
      "notes": "Direct registry match for 'toto'."
    }
  ],
  "environments_required": [
    {
      "label": "Launch site",
      "canonical_id": "balloon_launch_platform",
      "display_name": "balloon_launch_platform",
      "status": "canonical",
      "entity_kind": "environment",
      "resolution_score": 58,
      "source_path": "projects/wizard_of_oz/02_story_analysis/environment_breakdowns/chapters/CH017/balloon_launch_platform.md",
      "notes": "Chapter-local environment alias match for 'Launch site' (key_overlap=1, label_overlap=1, context_overlap=4)."
    },
    {
      "label": "Emerald City",
      "canonical_id": "emerald_city_palace_exterior",
      "display_name": "emerald_city_palace_exterior",
      "status": "canonical",
      "entity_kind": "city",
      "resolution_score": 104,
      "source_path": "projects/wizard_of_oz/02_story_analysis/environment_breakdowns/chapters/CH017/emerald_city_palace_exterior.md",
      "notes": "Chapter-local environment alias match for 'Emerald City' (key_overlap=2, label_overlap=2, context_overlap=4)."
    }
  ],
  "continuity_constraints": [
    "Precise timing of rope snap relative to Dorothy's proximity to the basket",
    "Consistent rate of vertical ascent for the balloon"
  ],
  "visual_coverage_families": [
    "Tracking shots of Dorothy running toward the basket",
    "High-angle/POV looking up at the ascending balloon",
    "Close-ups of snapping ropes and facial reactions",
    "Wide shots showing the shrinking balloon against the sky"
  ],
  "beat_list": [
    {
      "beat_id": "BT001",
      "summary": "Dorothy realizes Toto is missing and rushes toward the balloon",
      "purpose": "",
      "action_start": "Dorothy stops mid-conversation",
      "action_end": "Dorothy reaches the edge of the launch platform",
      "active_subjects": [
        "dorothy"
      ],
      "passive_subjects": [
        "the_scarecrow",
        "tin_woodman",
        "Lion",
        "oz"
      ],
      "spatial_context": "balloon_launch_platform",
      "blocking_hint": "Dorothy breaks away from the group toward the basket",
      "environment_subzone": "balloon_launch_platform",
      "continuity_focus": "Dorothy's distance from the basket must decrease steadily",
      "coverage_hint": "tracking shot",
      "coverage_priority": "high",
      "handoff_to_next": "BT002"
    },
    {
      "beat_id": "BT002",
      "summary": "The ropes snap prematurely",
      "purpose": "",
      "action_start": "Balloon begins to lift slightly",
      "action_end": "Ropes fall slack/snap",
      "active_subjects": [
        "oz"
      ],
      "passive_subjects": [
        "dorothy"
      ],
      "spatial_context": "balloon_launch_platform",
      "blocking_hint": "Focus on the connection between basket and ground",
      "environment_subzone": "balloon_launch_platform",
      "continuity_focus": "Timing of snap relative to Dorothy's reach",
      "coverage_hint": "close-up/insert",
      "coverage_priority": "critical",
      "handoff_to_next": "BT003"
    },
    {
      "beat_id": "BT003",
      "summary": "The balloon ascends rapidly, leaving everyone behind",
      "purpose": "",
      "action_start": "Balloon breaks contact with ground",
      "action_end": "Balloon is a small speck in the sky",
      "active_subjects": [
        "oz"
      ],
      "passive_subjects": [
        "dorothy",
        "the_scarecrow",
        "tin_woodman",
        "Lion"
      ],
      "spatial_context": "emerald_city_palace_exterior",
      "blocking_hint": "Group remains grounded, looking upward",
      "environment_subzone": "emerald_city_palace_exterior",
      "continuity_focus": "Speed of ascent must be rapid and consistent",
      "coverage_hint": "wide shot/high-angle POV",
      "coverage_priority": "medium",
      "handoff_to_next": "none"
    }
  ],
  "planned_shots": [
    {
      "planned_shot_id": "SH001",
      "beat_id": "BT001",
      "narrative_function": "establish urgency",
      "planned_shot_moment_summary": "Dorothy realizes Toto is missing and begins running",
      "primary_subject_seed": "dorothy",
      "secondary_subjects_seed": [
        "the_scarecrow",
        "tin_woodman",
        "Lion"
      ],
      "subject_visibility": "on_screen",
      "narration_mode": "none",
      "environment_subzone": "balloon_launch_platform",
      "planned_shot_required_anchor_1": "balloon_basket",
      "planned_shot_scale_proof_detail": "distance between Dorothy and basket",
      "start_state_seed": "Dorothy standing near group",
      "end_state_seed": "Dorothy mid-sprint",
      "action_seed": "running toward balloon",
      "blocking_seed": [
        "dorothy breaks from group toward basket"
      ],
      "shot_size": "medium_full",
      "camera_angle": "eye_level",
      "lens_family": "wide",
      "camera_motion": "track",
      "zoom_behavior": "none",
      "focus_strategy": "shallow_subject",
      "lighting_style": "diffuse_ambient",
      "primary_subject_angle": "front_three_quarter_right"
    },
    {
      "planned_shot_id": "SH002",
      "beat_id": "BT002",
      "narrative_function": "climax of tension",
      "planned_shot_moment_summary": "the ropes snap prematurely",
      "primary_subject_seed": "tether_ropes",
      "secondary_subjects_seed": [
        "dorothy"
      ],
      "subject_visibility": "on_screen",
      "narration_mode": "none",
      "environment_subzone": "balloon_launch_platform",
      "planned_shot_required_anchor_1": "tether_ropes",
      "planned_shot_scale_proof_detail": "tension in rope before snap",
      "start_state_seed": "ropes taut",
      "end_state_seed": "ropes frayed/snapped",
      "action_seed": "ropes snapping under tension",
      "blocking_seed": [
        "close up on tether point"
      ],
      "shot_size": "insert_detail",
      "camera_angle": "low_angle",
      "lens_family": "telephoto",
      "camera_motion": "locked_off",
      "zoom_behavior": "none",
      "focus_strategy": "deep_focus",
      "lighting_style": "hard_directional",
      "primary_subject_angle": "profile_left"
    },
    {
      "planned_shot_id": "SH003",
      "beat_id": "BT003",
      "narrative_function": "establish abandonment",
      "planned_shot_moment_summary": "balloon ascends rapidly into the sky",
      "primary_subject_seed": "oz",
      "secondary_subjects_seed": [
        "dorothy",
        "the_scarecrow",
        "tin_woodman",
        "Lion"
      ],
      "subject_visibility": "on_screen",
      "narration_mode": "none",
      "environment_subzone": "emerald_city_palace_exterior",
      "planned_shot_required_anchor_1": "balloon_basket",
      "planned_shot_scale_proof_detail": "balloon shrinking in frame",
      "start_state_seed": "balloon lifting off ground",
      "end_state_seed": "balloon high in sky",
      "action_seed": "rapid vertical ascent",
      "blocking_seed": [
        "group looking up from ground"
      ],
      "shot_size": "extreme_wide",
      "camera_angle": "high_angle",
      "lens_family": "ultra_wide",
      "camera_motion": "tilt",
      "zoom_behavior": "none",
      "focus_strategy": "deep_focus",
      "lighting_style": "diffuse_ambient",
      "primary_subject_angle": "back"
    }
  ],
  "unresolved_questions": [
    "Resolve Lion -> Lion"
  ],
  "evidence_refs": [
    {
      "source": "scene_breakdown",
      "chapter_id": "CH017",
      "scene_id": "CH017_SC004"
    },
    {
      "source": "scene_breakdown",
      "chapter_id": "CH017",
      "scene_id": "CH017_SC004"
    },
    {
      "source": "scene_breakdown",
      "chapter_id": "CH017",
      "scene_id": "CH017_SC004"
    },
    {
      "source": "scene_breakdown",
      "chapter_id": "CH017",
      "scene_id": "CH017_SC004"
    },
    {
      "source": "scene_breakdown",
      "chapter_id": "CH017",
      "scene_id": "CH017_SC004"
    },
    {
      "source": "chapter_summary",
      "chapter_id": "CH017",
      "source_path": "C:\\FilmCreator\\projects\\wizard_of_oz\\02_story_analysis\\chapter_analysis\\CH017_summary.md"
    },
    {
      "source": "book_index",
      "chapter_id": "CH017",
      "source_path": "projects/wizard_of_oz/01_source/chapters/CH017_chapter_xvii.md"
    },
    {
      "source": "book_index",
      "chapter_id": "CH005",
      "source_path": "projects/wizard_of_oz/01_source/chapters/CH005_chapter_v.md"
    },
    {
      "source": "book_index",
      "chapter_id": "CH003",
      "source_path": "projects/wizard_of_oz/01_source/chapters/CH003_chapter_iii.md"
    },
    {
      "source": "character_bible",
      "chapter_id": "CH017",
      "canonical_id": "dorothy"
    }
  ],
  "evidence_summary": [
    "[CH017_SC004] Purpose: The climax of the chapter and the tragic reversal of fortune.",
    "[CH017_SC004] Summary: As the balloon begins to lift, Dorothy realizes Toto is missing and rushes to find him. Just as she reaches the basket, the ropes snap prematurely. The balloon ascends rapidly into the sky with only Oz inside, leaving Dorothy and her...",
    "[CH017_SC004] Emotional arc: From frantic hope to sudden shock and abandonment.",
    "[CH017_SC004] Coverage: Tracking shots: Dorothy running toward the balloon. High-angle/POV shots: Looking up at the ascending balloon. Close-ups: The snapping ropes; Dorothy's face of realization/despair. Wide shot: The balloon shrinking into the sky, leavi...",
    "[CH017_SC004] Continuity: The timing of the rope snap relative to Dorothy's position; the height and speed of the balloon's ascent.",
    "[CH017] Chapter summary: **Setting:** The Throne Room and the exterior of the Palace in the Emerald City. **Characters:** - Dorothy: Longing to return to Kansas. - Oz (The Wizard): A \"humbug\" seeking to escape his life of deception by returni...",
    "[CH017] Chapter XVII (book index hit)",
    "[CH005] Chapter V (book index hit)",
    "[CH003] Chapter III (book index hit)",
    "Character dorothy: Dorothy is a young human girl characterized by an expressive face. While her initial attire is noted as having been green, she is primarily identified in her journey by white clothing or a white dress. Her most significant visual and func..."
  ],
  "storyboard_markdown": "# Scene Contract: CH017_SC004\n\n## Production Intent\nExecute the tragic separation of Dorothy and Oz via a mechanical failure of the balloon tethering system. The sequence must transition from high-energy movement to static despair, emphasizing the vertical distance growing between the characters on the ground and the ascending vessel.\n\n## Required Cast\n- dorothy (white clothing/dress)\n- oz (inside basket)\n- the_scarecrow\n- tin_woodman\n- Lion\n- toto (off-screen/searching)\n\n## Required Environments\n- balloon_launch_platform\n- emerald_city_palace_exterior\n\n## Continuity Constraints\n- Timing of rope snap relative to Dorothy's position.\n- Rate and height of the balloon's vertical ascent.\n\n## Beat List\n- BT001: Dorothy realizes Toto is missing and rushes toward the balloon.\n- BT002: The ropes snap prematurely.\n- BT003: The balloon ascends rapidly, leaving everyone behind.",
  "metadata": {
    "artifact_id": "CH017_SC004_SCENE_CONTRACT",
    "artifact_type": "scene_contract",
    "status": "generated",
    "source_fingerprint": "aaf5274caf45645837059927264f06392ad37743",
    "created_at_utc": "2026-04-27T08:53:48.961640+00:00",
    "updated_at_utc": "2026-04-27T08:53:48.962641+00:00",
    "upstream_dependencies": [
      {
        "dependency_type": "scene_breakdown",
        "dependency_id": "CH017_SC004",
        "version": "86f7f0faa204a43ac417acfbf95e8af0a538631e"
      },
      {
        "dependency_type": "character_resolutions",
        "dependency_id": "CH017_SC004",
        "version": "ef0f38120a77ee0583346ffb4c8871f987b5f40f"
      },
      {
        "dependency_type": "environment_resolutions",
        "dependency_id": "CH017_SC004",
        "version": "bd540bc1d60c25dcdb184d00a272c9463a775308"
      }
    ],
    "locked_fields": {},
    "manual_overrides": {},
    "revision_history": [
      {
        "timestamp_utc": "2026-04-27T08:54:33.243855+00:00",
        "action": "synthesized",
        "source_fingerprint": "aaf5274caf45645837059927264f06392ad37743"
      }
    ]
  }
}
