{
  "scene_id": "CH015_SC004",
  "chapter_id": "CH015",
  "scene_title": "SC004",
  "purpose": "The central reveal and subversion of the Wizard's power.",
  "summary": "The illusions vanish or are bypassed, revealing a small, ordinary man behind a curtain or machine. The \"Great Wizard\" is exposed as a mere humbug using stagecraft.",
  "emotional_arc": "Awe $\\rightarrow$ Disillusionment/Anger.",
  "production_intent": "Execute the visual transition from a grand, magical illusion to a mundane, mechanical reality. The sequence must strip away the perceived divinity of the Wizard by revealing the physical stagecraft and the smallness of the man behind it.",
  "scene_short_description": "Grand illusions vanish to reveal a small man operating mechanical stagecraft behind a curtain.",
  "scene_primary_scale_story_point": "The massive scale of the Wizard's illusion vs. the small physical stature of oz.",
  "scene_required_anchor_catalog": [
    "mechanical lever/machine",
    "curtain/backdrop"
  ],
  "scene_start_state": "High-status magical atmosphere with grand illusions active.",
  "scene_end_state": "Low-status workshop atmosphere with the man exposed and characters reacting in anger.",
  "dominant_action_line": "The bypass or removal of the illusion to reveal the humbug.",
  "scene_spatial_layout": [
    "Grand hall foreground for travelers",
    "Behind-the-scenes/workshop area behind a curtain/machine barrier"
  ],
  "character_spatial_map": [
    "dorothy, the_scarecrow, tin_woodman, cowardly_lion positioned in throne_room_grand_hall facing the illusion",
    "oz positioned behind the machine/curtain in the workshop subzone"
  ],
  "environment_subzones": [
    "throne_room_grand_hall (illusion zone)",
    "workshop (behind-the-scenes area)"
  ],
  "entry_vectors": [
    "travelers enter from hall into the presence of the Wizard"
  ],
  "exit_vectors": [
    "none specified"
  ],
  "beat_transition_map": [
    "BT001 -> BT002: Visual collapse of illusion",
    "BT002 -> BT003: Physical reveal of oz"
  ],
  "characters_required": [
    {
      "label": "Dorothy",
      "canonical_id": "dorothy",
      "display_name": "dorothy",
      "status": "canonical",
      "entity_kind": "individual",
      "resolution_score": 138,
      "source_path": "projects/wizard_of_oz/02_story_analysis/character_breakdowns/chapters/CH015/dorothy.md",
      "notes": "Direct registry match for 'dorothy'."
    },
    {
      "label": "Scarecrow",
      "canonical_id": "the_scarecrow",
      "display_name": "the_scarecrow",
      "status": "canonical",
      "entity_kind": "individual",
      "resolution_score": 186,
      "source_path": "projects/wizard_of_oz/02_story_analysis/character_breakdowns/chapters/CH003/the_scarecrow.md",
      "notes": "asset id exactly matches canonical id | query matches alias 'scarecrow'"
    },
    {
      "label": "Tin Woodman",
      "canonical_id": "tin_woodman",
      "display_name": "tin_woodman",
      "status": "canonical",
      "entity_kind": "individual",
      "resolution_score": 138,
      "source_path": "projects/wizard_of_oz/02_story_analysis/character_breakdowns/chapters/CH015/tin_woodman.md",
      "notes": "Direct registry match for 'tin_woodman'."
    },
    {
      "label": "Cowardly Lion",
      "canonical_id": "cowardly_lion",
      "display_name": "cowardly_lion",
      "status": "canonical",
      "entity_kind": "individual",
      "resolution_score": 138,
      "source_path": "projects/wizard_of_oz/02_story_analysis/character_breakdowns/chapters/CH015/cowardly_lion.md",
      "notes": "Direct registry match for 'cowardly_lion'."
    },
    {
      "label": "Oz (The Man)",
      "canonical_id": "oz",
      "display_name": "oz",
      "status": "canonical",
      "entity_kind": "individual",
      "resolution_score": 138,
      "source_path": "projects/wizard_of_oz/02_story_analysis/character_breakdowns/chapters/CH015/oz.md",
      "notes": "Direct registry match for 'oz'."
    }
  ],
  "environments_required": [
    {
      "label": "The Throne Room / Behind the scenes area",
      "canonical_id": "throne_room_grand_hall",
      "display_name": "throne_room_grand_hall",
      "status": "canonical",
      "entity_kind": "environment",
      "resolution_score": 92,
      "source_path": "projects/wizard_of_oz/02_story_analysis/environment_breakdowns/chapters/CH015/throne_room_grand_hall.md",
      "notes": "Chapter-local environment alias match for 'The Throne Room / Behind the scenes area' (key_overlap=2, label_overlap=2, context_overlap=4)."
    }
  ],
  "continuity_constraints": [
    "Transition from magical lighting to mundane workshop lighting"
  ],
  "visual_coverage_families": [
    "Reveal shot (moving from illusion to man)",
    "Reaction medium shots (characters)",
    "Detail close-ups (mechanical props and levers)"
  ],
  "beat_list": [
    {
      "beat_id": "BT001",
      "summary": "The peak of the Wizard's illusion",
      "purpose": "",
      "action_start": "grand magical display active",
      "action_end": "illusion begins to fail",
      "active_subjects": [
        "dorothy",
        "the_scarecrow",
        "tin_woodman",
        "cowardly_lion"
      ],
      "passive_subjects": [
        "oz"
      ],
      "spatial_context": "throne_room_grand_hall",
      "blocking_hint": "characters looking upward/forward in awe",
      "environment_subzone": "throne_room_grand_hall",
      "continuity_focus": "magical lighting",
      "coverage_hint": "wide shot of the spectacle",
      "coverage_priority": "high",
      "handoff_to_next": "BT002"
    },
    {
      "beat_id": "BT002",
      "summary": "The collapse of the facade",
      "purpose": "",
      "action_start": "illusion flickers and vanishes",
      "action_end": "the machine/man is visible",
      "active_subjects": [
        "oz"
      ],
      "passive_subjects": [
        "dorothy",
        "the_scarecrow",
        "tin_woodman",
        "cowardly_lion"
      ],
      "spatial_context": "transition from hall to workshop area",
      "blocking_hint": "oz revealed behind mechanical props",
      "environment_subzone": "workshop",
      "continuity_focus": "shift from magical to mundane lighting",
      "coverage_hint": "reveal shot/close-ups on levers",
      "coverage_priority": "high",
      "handoff_to_next": "BT003"
    },
    {
      "beat_id": "BT003",
      "summary": "The realization of the humbug",
      "purpose": "",
      "action_start": "characters see the small man",
      "action_end": "anger and disillusionment set in",
      "active_subjects": [
        "dorothy",
        "the_scarecrow",
        "tin_woodman",
        "cowardly_lion"
      ],
      "passive_subjects": [
        "oz"
      ],
      "spatial_context": "throne_room_grand_hall",
      "blocking_hint": "characters facing the revealed machine/man",
      "environment_subzone": "throne_room_grand_hall",
      "continuity_focus": "mundane workshop lighting",
      "coverage_hint": "medium reaction shots",
      "coverage_priority": "medium",
      "handoff_to_next": "end_of_scene"
    }
  ],
  "planned_shots": [
    {
      "planned_shot_id": "SH001",
      "beat_id": "BT001",
      "narrative_function": "establish awe",
      "planned_shot_moment_summary": "the grand illusion is at its peak",
      "primary_subject_seed": "throne_room_grand_hall",
      "secondary_subjects_seed": [],
      "subject_visibility": "on_screen",
      "narration_mode": "in_scene_speaker",
      "environment_subzone": "throne_room_grand_hall",
      "planned_shot_required_anchor_1": "curtain/backdrop",
      "planned_shot_scale_proof_detail": "massive scale of illusion vs characters",
      "start_state_seed": "magical lighting active",
      "end_state_seed": "lighting begins to shift",
      "action_seed": "illusion flickers",
      "blocking_seed": [
        "characters looking up in awe"
      ],
      "shot_size": "wide",
      "camera_angle": "low_angle",
      "lens_family": "wide",
      "camera_motion": "push_in",
      "zoom_behavior": "none",
      "focus_strategy": "deep_focus",
      "lighting_style": "high_contrast_ceremonial",
      "primary_subject_angle": "front_three_quarter_left"
    },
    {
      "planned_shot_id": "SH002",
      "beat_id": "BT002",
      "narrative_function": "reveal truth",
      "planned_shot_moment_summary": "the illusion vanishes to show the machine",
      "primary_subject_seed": "oz",
      "secondary_subjects_seed": [],
      "subject_visibility": "on_screen",
      "narration_mode": "in_scene_speaker",
      "environment_subzone": "workshop",
      "planned_shot_required_anchor_1": "mechanical lever/machine",
      "planned_shot_scale_proof_detail": "small man vs large machine",
      "start_state_seed": "magical lighting fails",
      "end_state_seed": "mundane workshop lighting active",
      "action_seed": "curtain falls or illusion fades",
      "blocking_seed": [
        "oz revealed behind levers"
      ],
      "shot_size": "medium_full",
      "camera_angle": "eye_level",
      "lens_family": "normal",
      "camera_motion": "track",
      "zoom_behavior": "none",
      "focus_strategy": "rack_focus",
      "lighting_style": "diffuse_ambient",
      "primary_subject_angle": "front"
    },
    {
      "planned_shot_id": "SH003",
      "beat_id": "BT003",
      "narrative_function": "character reaction",
      "planned_shot_moment_summary": "the travelers realize the truth",
      "primary_subject_seed": "dorothy",
      "secondary_subjects_seed": [],
      "subject_visibility": "on_screen",
      "narration_mode": "in_scene_speaker",
      "environment_subzone": "throne_room_grand_hall",
      "planned_shot_required_anchor_1": "curtain/backdrop",
      "planned_shot_scale_proof_detail": "none",
      "start_state_seed": "shocked expression",
      "end_state_seed": "angry/disillusioned expression",
      "action_seed": "characters react to the humbug",
      "blocking_seed": [
        "dorothy and companions reacting in group"
      ],
      "shot_size": "medium_close",
      "camera_angle": "eye_level",
      "lens_family": "portrait",
      "camera_motion": "locked_off",
      "zoom_behavior": "subtle_in",
      "focus_strategy": "shallow_subject",
      "lighting_style": "diffuse_ambient",
      "primary_subject_angle": "front_three_quarter_right"
    }
  ],
  "unresolved_questions": [],
  "evidence_refs": [
    {
      "source": "scene_breakdown",
      "chapter_id": "CH015",
      "scene_id": "CH015_SC004"
    },
    {
      "source": "scene_breakdown",
      "chapter_id": "CH015",
      "scene_id": "CH015_SC004"
    },
    {
      "source": "scene_breakdown",
      "chapter_id": "CH015",
      "scene_id": "CH015_SC004"
    },
    {
      "source": "scene_breakdown",
      "chapter_id": "CH015",
      "scene_id": "CH015_SC004"
    },
    {
      "source": "scene_breakdown",
      "chapter_id": "CH015",
      "scene_id": "CH015_SC004"
    },
    {
      "source": "chapter_summary",
      "chapter_id": "CH015",
      "source_path": "C:\\FilmCreator\\projects\\wizard_of_oz\\02_story_analysis\\chapter_analysis\\CH015_summary.md"
    },
    {
      "source": "book_index",
      "chapter_id": "CH015",
      "source_path": "projects/wizard_of_oz/01_source/chapters/CH015_chapter_xv.md"
    },
    {
      "source": "book_index",
      "chapter_id": "CH010",
      "source_path": "projects/wizard_of_oz/01_source/chapters/CH010_chapter_x.md"
    },
    {
      "source": "book_index",
      "chapter_id": "CH011",
      "source_path": "projects/wizard_of_oz/01_source/chapters/CH011_chapter_xi.md"
    },
    {
      "source": "character_bible",
      "chapter_id": "CH015",
      "canonical_id": "dorothy"
    }
  ],
  "evidence_summary": [
    "[CH015_SC004] Purpose: The central reveal and subversion of the Wizard's power.",
    "[CH015_SC004] Summary: The illusions vanish or are bypassed, revealing a small, ordinary man behind a curtain or machine. The \"Great Wizard\" is exposed as a mere humbug using stagecraft.",
    "[CH015_SC004] Emotional arc: Awe $\\rightarrow$ Disillusionment/Anger.",
    "[CH015_SC004] Coverage: Reveal shot (moving from the illusion to the man); medium shots of the characters' reactions; close-ups on the mechanical props and levers.",
    "[CH015_SC004] Continuity: The transition from \"magical\" lighting to \"mundane\" workshop lighting.",
    "[CH015] Chapter summary: **Summary:** After returning to the Emerald City and reporting the death of the Wicked Witch of the West, Dorothy and her companions demand that the Wizard fulfill his promises. After a period of tense waiting and a t...",
    "[CH015] Chapter XV (book index hit)",
    "[CH010] Chapter X (book index hit)",
    "[CH011] Chapter XI (book index hit)",
    "Character dorothy: Dorothy is a young human girl characterized by an expressive face and the appearance of a weary traveler. Her visual identity evolves during her journey, transitioning from previously green clothing to a white dress or clothing. She is mo..."
  ],
  "storyboard_markdown": "# Scene Contract: CH015_SC004\n\n## Production Intent\nExecute the visual transition from a grand, magical illusion to a mundane, mechanical reality. The sequence must strip away the perceived divinity of the Wizard by revealing the physical stagecraft and the smallness of the man behind it.\n\n## Required Cast\n- dorothy\n- the_scarecrow\n- tin_woodman\n- cowardly_lion\n- oz\n\n## Required Environments\n- throne_room_grand_hall (including workshop subzone)\n\n## Continuity Constraints\n- Transition from \"magical\" lighting to \"mundane\" workshop lighting.\n\n## Beat List\n- BT001: The peak of the Wizard's illusion.\n- BT002: The collapse of the facade/reveal of the machine.\n- BT003: The realization and reaction of the travelers.",
  "metadata": {
    "artifact_id": "CH015_SC004_SCENE_CONTRACT",
    "artifact_type": "scene_contract",
    "status": "generated",
    "source_fingerprint": "107fdccfb7a41e97ebd71b4550cca00be709f17e",
    "created_at_utc": "2026-04-27T08:47:13.084671+00:00",
    "updated_at_utc": "2026-04-27T13:50:09.436859+00:00",
    "upstream_dependencies": [
      {
        "dependency_type": "scene_breakdown",
        "dependency_id": "CH015_SC004",
        "version": "96cc6eadc69eaacd5d69973340139880c31f0098"
      },
      {
        "dependency_type": "character_resolutions",
        "dependency_id": "CH015_SC004",
        "version": "1bcbba92cd143afb36478344a4e914ff24a88878"
      },
      {
        "dependency_type": "environment_resolutions",
        "dependency_id": "CH015_SC004",
        "version": "60e8bff50903edb11006f62315ebfdc575af2d70"
      }
    ],
    "locked_fields": {},
    "manual_overrides": {},
    "revision_history": [
      {
        "timestamp_utc": "2026-04-27T08:47:55.111607+00:00",
        "action": "synthesized",
        "source_fingerprint": "989b041184ea7f9d3f2df85db4842a1a80ae762b"
      },
      {
        "timestamp_utc": "2026-04-27T13:50:51.757686+00:00",
        "action": "synthesized",
        "source_fingerprint": "107fdccfb7a41e97ebd71b4550cca00be709f17e"
      }
    ]
  }
}
