[
  {
    "dialogue_id": "CH014_DLG030",
    "chapter_id": "CH014",
    "paragraph_index": 26,
    "quote_index": 1,
    "source_ref": "CH014:p026:q01",
    "source_path": "projects/wizard_of_oz/01_source/chapters/CH014_chapter_xiv.md",
    "dialogue_text": "What is your command?",
    "source_excerpt": "The King bowed low before Dorothy, and asked, \"What is your command?\"",
    "speaker": {
      "speaker_label": "unresolved",
      "canonical_id": null,
      "display_name": "unresolved",
      "status": "unresolved",
      "entity_kind": "unknown",
      "confidence": 0.0,
      "resolution_method": "unresolved",
      "notes": "No canonical speaker could be inferred from the source context."
    },
    "scene_id": "CH014_SC003",
    "shot_id": "SH009",
    "clip_id": "CL009",
    "scene_binding_confidence": 0.55,
    "shot_binding_confidence": 0.45,
    "binding_method": "shot_sequence",
    "review_notes": [
      "Speaker could not be resolved from the source context."
    ]
  }
]
