[
  {
    "dialogue_id": "CH004_DLG013",
    "chapter_id": "CH004",
    "paragraph_index": 17,
    "quote_index": 1,
    "source_ref": "CH004:p017:q01",
    "source_path": "projects/wizard_of_oz/01_source/chapters/CH004_chapter_iv.md",
    "dialogue_text": "'Now I'll make the eyes,'",
    "source_excerpt": "\"'Now I'll make the eyes,'\" said the farmer. So he painted my right eye, and as soon as it was finished I found myself looking at him and at everything around me with a great deal of curiosity, for this was my first glimpse of the world.",
    "speaker": {
      "speaker_label": "unresolved",
      "canonical_id": null,
      "display_name": "unresolved",
      "status": "unresolved",
      "entity_kind": "unknown",
      "confidence": 0.0,
      "resolution_method": "unresolved",
      "notes": "No canonical speaker could be inferred from the source context."
    },
    "scene_id": "CH004_SC003",
    "shot_id": "SH001",
    "clip_id": "CL001",
    "scene_binding_confidence": 0.55,
    "shot_binding_confidence": 0.45,
    "binding_method": "shot_sequence",
    "review_notes": [
      "Speaker could not be resolved from the source context."
    ]
  }
]
