{
  "scene_id": "CH007_SC002",
  "chapter_id": "CH007",
  "binding_mode": "scene_level",
  "resolved_characters": [
    {
      "label": "Dorothy",
      "canonical_id": "dorothy",
      "display_name": "dorothy",
      "status": "canonical",
      "entity_kind": "individual",
      "resolution_score": 138,
      "source_path": "projects/wizard_of_oz/02_story_analysis/character_breakdowns/chapters/CH007/dorothy.md",
      "notes": "Direct registry match for 'dorothy'."
    },
    {
      "label": "Toto",
      "canonical_id": "toto",
      "display_name": "toto",
      "status": "canonical",
      "entity_kind": "individual",
      "resolution_score": 138,
      "source_path": "projects/wizard_of_oz/02_story_analysis/character_breakdowns/chapters/CH007/toto.md",
      "notes": "Direct registry match for 'toto'."
    },
    {
      "label": "Scarecrow",
      "canonical_id": "the_scarecrow",
      "display_name": "the_scarecrow",
      "status": "canonical",
      "entity_kind": "individual",
      "resolution_score": 186,
      "source_path": "projects/wizard_of_oz/02_story_analysis/character_breakdowns/chapters/CH007/the_scarecrow.md",
      "notes": "asset id exactly matches canonical id | query matches alias 'scarecrow'"
    },
    {
      "label": "Tin Woodman",
      "canonical_id": "tin_woodman",
      "display_name": "tin_woodman",
      "status": "canonical",
      "entity_kind": "individual",
      "resolution_score": 138,
      "source_path": "projects/wizard_of_oz/02_story_analysis/character_breakdowns/chapters/CH007/tin_woodman.md",
      "notes": "Direct registry match for 'tin_woodman'."
    },
    {
      "label": "Cowardly Lion",
      "canonical_id": "cowardly_lion",
      "display_name": "cowardly_lion",
      "status": "canonical",
      "entity_kind": "individual",
      "resolution_score": 138,
      "source_path": "projects/wizard_of_oz/02_story_analysis/character_breakdowns/chapters/CH007/cowardly_lion.md",
      "notes": "Direct registry match for 'cowardly_lion'."
    }
  ],
  "resolved_environment": {
    "label": "Deep Forest Chasm/Ditch",
    "canonical_id": "arizona_dense_forest_and_ditches",
    "display_name": "arizona_dense_forest_and_ditches",
    "status": "canonical",
    "entity_kind": "environment",
    "resolution_score": 100,
    "source_path": "projects/wizard_of_oz/02_story_analysis/environment_breakdowns/chapters/CH007/arizona_dense_forest_and_ditches.md",
    "notes": "Chapter-local environment alias match for 'Deep Forest Chasm/Ditch' (key_overlap=1, label_overlap=4, context_overlap=4)."
  },
  "beat_environment_overrides": [],
  "candidate_environment_ids": [
    "arizona_dense_forest_and_ditches"
  ],
  "future_environment_requests": [],
  "review_flags": [],
  "notes": [],
  "evidence_refs": [
    {
      "source": "scene_breakdown",
      "chapter_id": "CH007",
      "scene_id": "CH007_SC002"
    },
    {
      "source": "scene_breakdown",
      "chapter_id": "CH007",
      "scene_id": "CH007_SC002"
    },
    {
      "source": "scene_breakdown",
      "chapter_id": "CH007",
      "scene_id": "CH007_SC002"
    },
    {
      "source": "scene_breakdown",
      "chapter_id": "CH007",
      "scene_id": "CH007_SC002"
    },
    {
      "source": "scene_breakdown",
      "chapter_id": "CH007",
      "scene_id": "CH007_SC002"
    },
    {
      "source": "chapter_summary",
      "chapter_id": "CH007",
      "source_path": "C:\\FilmCreator\\projects\\wizard_of_oz\\02_story_analysis\\chapter_analysis\\CH007_summary.md"
    },
    {
      "source": "book_index",
      "chapter_id": "CH007",
      "source_path": "projects/wizard_of_oz/01_source/chapters/CH007_chapter_vii.md"
    },
    {
      "source": "book_index",
      "chapter_id": "CH006",
      "source_path": "projects/wizard_of_oz/01_source/chapters/CH006_chapter_vi.md"
    },
    {
      "source": "book_index",
      "chapter_id": "CH009",
      "source_path": "projects/wizard_of_oz/01_source/chapters/CH009_chapter_ix.md"
    },
    {
      "source": "character_bible",
      "chapter_id": "CH007",
      "canonical_id": "dorothy"
    }
  ],
  "evidence_summary": [
    "[CH007_SC002] Purpose: Introduce the first physical obstacle and showcase the Lion's unexpected utility.",
    "[CH007_SC002] Summary: The group encounters a wide, deep chasm. The Cowardly Lion overcomes his fear to leap across the gap, acting as a ferry by carrying each companion on his back one by one.",
    "[CH007_SC002] Emotional arc: Anxiety $\\rightarrow$ Relief/Awe.",
    "[CH007_SC002] Coverage: Low-angle shots of the deep ditch to emphasize scale. Dynamic tracking shots following the Lion's leaps. Reaction shots from the characters waiting at the edge.",
    "[CH007_SC002] Continuity: The depth and width of the chasm; the order in which characters are carried across.",
    "[CH007] Chapter summary: **Setting:** A dense forest containing deep ditches, a riverbank, and eventually a view of a beautiful, fruit-filled meadow across a swift river. **Characters:** Dorothy (and Toto), Scarecrow, Tin Woodman, Cowardly Li...",
    "[CH007] Chapter VII (book index hit)",
    "[CH006] Chapter VI (book index hit)",
    "[CH009] Chapter IX (book index hit)",
    "Character dorothy: Dorothy is a young human girl characterized by an expressive face and the appearance of a weary traveler. Her visual identity evolves during her journey, transitioning from previously green clothing to a white dress or clothing. She is mo..."
  ],
  "metadata": {
    "artifact_id": "CH007_SC002_SCENE_BINDINGS",
    "artifact_type": "scene_binding",
    "status": "generated",
    "source_fingerprint": "2ce9df8e9e726565c3ea18040fae6b08bc8bae44",
    "created_at_utc": "2026-04-27T09:16:15.366145+00:00",
    "updated_at_utc": "2026-04-27T14:19:47.178287+00:00",
    "upstream_dependencies": [
      {
        "dependency_type": "scene_contract",
        "dependency_id": "CH007_SC002",
        "version": "1553f236b6fe3d5955b89be848d06b7f2d02f408"
      }
    ],
    "locked_fields": {},
    "manual_overrides": {},
    "revision_history": [
      {
        "timestamp_utc": "2026-04-27T09:16:15.367145+00:00",
        "action": "synthesized",
        "source_fingerprint": "63d482e0cd5e319fc179aebe017e01606d383c70"
      },
      {
        "timestamp_utc": "2026-04-27T14:19:47.178287+00:00",
        "action": "synthesized",
        "source_fingerprint": "2ce9df8e9e726565c3ea18040fae6b08bc8bae44"
      }
    ]
  }
}
